CHANGELOG
LICENSE.txt
MANIFEST.in
README.rst
setup.py
Wraptor.egg-info/PKG-INFO
Wraptor.egg-info/SOURCES.txt
Wraptor.egg-info/dependency_links.txt
Wraptor.egg-info/top_level.txt
wraptor/__init__.py
wraptor/context/__init__.py
wraptor/context/maybe.py
wraptor/context/throttle.py
wraptor/context/timer.py
wraptor/context/test/__init__.py
wraptor/context/test/test_maybe.py
wraptor/context/test/test_throttle.py
wraptor/context/test/test_timer.py
wraptor/decorators/__init__.py
wraptor/decorators/exception_catcher.py
wraptor/decorators/memoize.py
wraptor/decorators/throttle.py
wraptor/decorators/timeout.py
wraptor/decorators/test/__init__.py
wraptor/decorators/test/test_called_with_args.py
wraptor/decorators/test/test_exception_catcher.py
wraptor/decorators/test/test_memoize.py
wraptor/decorators/test/test_throttle.py
wraptor/decorators/test/test_timeout.py
wraptor/test/__init__.py