Metadata-Version: 1.0
Name: Wraptor
Version: 0.6.0
Summary: Useful decorators and other utility functions.
Home-page: http://github.com/carlsverre/wraptor
Author: Carl Sverre
Author-email: carl@carlsverre.com
License: LICENSE.txt
Platform: UNKNOWN
